requests_wininet/__init__.py
requests_wininet-0.1.7.dist-info/METADATA
requests_wininet-0.1.7.dist-info/WHEEL
requests_wininet-0.1.7.dist-info/RECORD
