Metadata-Version: 2.3
Name: requests-wininet
Version: 0.1.7
Summary: Implements Window's WinINet API for python requests
License: Apache-2.0
Author: Curtis Ruck
Requires-Python: >=3.9
Classifier: License :: OSI Approved :: Apache Software License
Classifier: Programming Language :: Python :: 3
Classifier: Programming Language :: Python :: 3.9
Classifier: Programming Language :: Python :: 3.10
Classifier: Programming Language :: Python :: 3.11
Classifier: Programming Language :: Python :: 3.12
Classifier: Programming Language :: Python :: 3.13
Requires-Dist: pywincrypt32 (>=0.1.0,<0.2.0)
Requires-Dist: requests (>=2.27.0,<3.0.0)
Project-URL: Issues, https://github.com/ruckc/requests-wininet/issues
Project-URL: Repository, https://github.com/ruckc/requests-wininet
